{"_prov": {"source": "U.S. Census Bureau, ACS 2019-2023 5-year (tables B01001 age/sex, B03002 race/ethnicity), via Census API", "url": "https://data.census.gov/table/ACSDT5Y2023.B03002?g=610XX00US36020", "retrieved": "2026-07-15 23:48Z", "method": "SD-20 = state legislative district (upper) 020. 'NYC' = sum of the five county geographies (Bronx 005, Kings 047, New York 061, Queens 081, Richmond 085). Shares computed from raw counts.", "caveats": "ACS = survey ESTIMATES with margins of error (not shown here \u2014 that omission is itself a discussion point). Race categories follow B03002: White/Black/Asian are alone, non-Hispanic; Hispanic is all races."}, "age": {"groups": ["Under 18", "18-34", "35-54", "55-74", "75+"], "sd20_pct": [19.20914140770467, 26.905107537744676, 28.24392836826743, 19.882126570946312, 5.759696115336912], "nyc_pct": [20.433956357540602, 25.014190598109344, 26.232562355848298, 21.520931513836803, 6.7983591746649505]}, "race": {"labels": ["White (non-Hisp.)", "Black (non-Hisp.)", "Hispanic (any race)", "Asian (non-Hisp.)", "Other / multiracial"], "sd20_pct": [33.7, 43.7, 11.8, 4.3, 6.5], "nyc_pct": [31.3, 20.8, 28.4, 14.5, 4.9]}}